psutil/__init__.py
psutil/_common.py
psutil/_ntuples.py
psutil/_psaix.py
psutil/_psbsd.py
psutil/_pslinux.py
psutil/_psosx.py
psutil/_psposix.py
psutil/_pssunos.py
psutil/_psutil_linux.cpython-314t-x86_64-linux-gnu.so
psutil/_pswindows.py
psutil-7.2.1.dist-info/METADATA
psutil-7.2.1.dist-info/WHEEL
psutil-7.2.1.dist-info/top_level.txt
psutil-7.2.1.dist-info/RECORD
psutil-7.2.1.dist-info/licenses/LICENSE
