Metadata-Version: 2.4
Name: psutil
Version: 7.2.1
Summary: Cross-platform lib for process and system monitoring.
Home-page: https://github.com/giampaolo/psutil
Author: Giampaolo Rodola
Author-email: g.rodola@gmail.com
License: BSD-3-Clause
Keywords: ps,top,kill,free,lsof,netstat,nice,tty,ionice,uptime,taskmgr,process,df,iotop,iostat,ifconfig,taskset,who,pidof,pmap,smem,pstree,monitoring,ulimit,prlimit,smem,performance,metrics,agent,observability
Platform: Platform Independent
Classifier: Development Status :: 5 - Production/Stable
Classifier: Environment :: Console
Classifier: Intended Audience :: Developers
Classifier: Intended Audience :: Information Technology
Classifier: Intended Audience :: System Administrators
Classifier: Operating System :: MacOS :: MacOS X
Classifier: Operating System :: Microsoft :: Windows :: Windows 10
Classifier: Operating System :: Microsoft :: Windows :: Windows 11
Classifier: Operating System :: Microsoft :: Windows :: Windows 7
Classifier: Operating System :: Microsoft :: Windows :: Windows 8
Classifier: Operating System :: Microsoft :: Windows :: Windows 8.1
Classifier: Operating System :: Microsoft :: Windows :: Windows Server 2003
Classifier: Operating System :: Microsoft :: Windows :: Windows Server 2008
Classifier: Operating System :: Microsoft :: Windows :: Windows Vista
Classifier: Operating System :: Microsoft :: Windows
Classifier: Operating System :: Microsoft
Classifier: Operating System :: OS Independent
Classifier: Operating System :: POSIX :: AIX
Classifier: Operating System :: POSIX :: BSD :: FreeBSD
Classifier: Operating System :: POSIX :: BSD :: NetBSD
Classifier: Operating System :: POSIX :: BSD :: OpenBSD
Classifier: Operating System :: POSIX :: BSD
Classifier: Operating System :: POSIX :: Linux
Classifier: Operating System :: POSIX :: SunOS/Solaris
Classifier: Operating System :: POSIX
Classifier: Programming Language :: C
Classifier: Programming Language :: Python :: 3
Classifier: Programming Language :: Python :: Implementation :: CPython
Classifier: Programming Language :: Python :: Implementation :: PyPy
Classifier: Programming Language :: Python
Classifier: Topic :: Software Development :: Libraries :: Python Modules
Classifier: Topic :: Software Development :: Libraries
Classifier: Topic :: System :: Benchmark
Classifier: Topic :: System :: Hardware
Classifier: Topic :: System :: Monitoring
Classifier: Topic :: System :: Networking :: Monitoring :: Hardware Watchdog
Classifier: Topic :: System :: Networking :: Monitoring
Classifier: Topic :: System :: Networking
Classifier: Topic :: System :: Operating System
Classifier: Topic :: System :: Systems Administration
Classifier: Topic :: Utilities
Requires-Python: >=3.6
License-File: LICENSE
Provides-Extra: dev
Requires-Dist: psleak; extra == "dev"
Requires-Dist: pytest; extra == "dev"
Requires-Dist: pytest-instafail; extra == "dev"
Requires-Dist: pytest-xdist; extra == "dev"
Requires-Dist: setuptools; extra == "dev"
Requires-Dist: abi3audit; extra == "dev"
Requires-Dist: black; extra == "dev"
Requires-Dist: check-manifest; extra == "dev"
Requires-Dist: coverage; extra == "dev"
Requires-Dist: packaging; extra == "dev"
Requires-Dist: pylint; extra == "dev"
Requires-Dist: pyperf; extra == "dev"
Requires-Dist: pypinfo; extra == "dev"
Requires-Dist: pytest-cov; extra == "dev"
Requires-Dist: requests; extra == "dev"
Requires-Dist: rstcheck; extra == "dev"
Requires-Dist: ruff; extra == "dev"
Requires-Dist: sphinx; extra == "dev"
Requires-Dist: sphinx_rtd_theme; extra == "dev"
Requires-Dist: toml-sort; extra == "dev"
Requires-Dist: twine; extra == "dev"
Requires-Dist: validate-pyproject[all]; extra == "dev"
Requires-Dist: virtualenv; extra == "dev"
Requires-Dist: vulture; extra == "dev"
Requires-Dist: wheel; extra == "dev"
Provides-Extra: test
Requires-Dist: psleak; extra == "test"
Requires-Dist: pytest; extra == "test"
Requires-Dist: pytest-instafail; extra == "test"
Requires-Dist: pytest-xdist; extra == "test"
Requires-Dist: setuptools; extra == "test"
Dynamic: author
Dynamic: author-email
Dynamic: classifier
Dynamic: description
Dynamic: description-content-type
Dynamic: home-page
Dynamic: keywords
Dynamic: license
Dynamic: license-file
Dynamic: platform
Dynamic: provides-extra
Dynamic: requires-python
Dynamic: summary
